auntminnieupdate/__init__.py
auntminnieupdate-2.0.0.dist-info/LICENSE
auntminnieupdate-2.0.0.dist-info/METADATA
auntminnieupdate-2.0.0.dist-info/WHEEL
auntminnieupdate-2.0.0.dist-info/top_level.txt
auntminnieupdate-2.0.0.dist-info/RECORD
