Metadata-Version: 2.1
Name: auntminnieupdate
Version: 2.0.0
Summary: this package for scraping auntminnie recent news, webinars and radiology conference
Home-page: https://github.com/senchooo/auntminnnie-update
Author: Sencho Parameswara
Author-email: senchoparameswara@gmail.com
License: UNKNOWN
Project-URL: MyWeb, https://senchooo.com
Platform: UNKNOWN
Classifier: Programming Language :: Python :: 3
Classifier: License :: OSI Approved :: GNU Lesser General Public License v3 (LGPLv3)
Classifier: Operating System :: OS Independent
Classifier: Development Status :: 4 - Beta
Requires-Python: >=3.6
License-File: LICENSE
